ohm_led/__init__.py
ohm_led/device.py
ohm_led/discovery.py
ohm_led/error.py
ohm_made-0.0.7.dist-info/LICENSE
ohm_made-0.0.7.dist-info/METADATA
ohm_made-0.0.7.dist-info/WHEEL
ohm_made-0.0.7.dist-info/top_level.txt
ohm_made-0.0.7.dist-info/RECORD
